copytree/__init__.py
copytree/main.py
copytree_cli-0.2.0.dist-info/LICENSE
copytree_cli-0.2.0.dist-info/METADATA
copytree_cli-0.2.0.dist-info/WHEEL
copytree_cli-0.2.0.dist-info/entry_points.txt
copytree_cli-0.2.0.dist-info/top_level.txt
copytree_cli-0.2.0.dist-info/RECORD
