Metadata-Version: 2.1
Name: copytree-cli
Version: 0.2.0
Summary: A tool to copy directory trees
Home-page: https://github.com/meepstertron/copytree
Author: Meepsterton
Author-email: jan.koch@hexagonical.ch
Classifier: Programming Language :: Python :: 3
Classifier: License :: OSI Approved :: MIT License
Classifier: Operating System :: OS Independent
Requires-Python: >=3.6
License-File: LICENSE
